example/__init__.py
example/example.py
ezdir/__init__.py
ezdir/_version.py
ezdir/changer.py
ezdir/util/__init__.py
ezdir/util/system_folders.py
tests/__init__.py
tests/test_changer.py
ezdir-0.3.0.dist-info/LICENSE
ezdir-0.3.0.dist-info/METADATA
ezdir-0.3.0.dist-info/WHEEL
ezdir-0.3.0.dist-info/top_level.txt
ezdir-0.3.0.dist-info/RECORD
