Metadata-Version: 2.1
Name: ezdir
Version: 0.3.0
Summary: Change working directory up a number of levels or to a named folder
Home-page: https://github.com/mshodge/ezdir
Author: Michael Hodge
Author-email: michaelstvnhodge@gmail.com
Keywords: os,directory,path,utility
Classifier: Programming Language :: Python :: 3
Classifier: License :: OSI Approved :: MIT License
Classifier: Operating System :: OS Independent
Requires-Python: >=3.6
License-File: LICENSE
